nsmr/__init__.py
nsmr/envs/NsmrGymEnv.py
nsmr/envs/NsmrMinPoolingGymEnv.py
nsmr/envs/NsmrSimpleGymEnv.py
nsmr/envs/__init__.py
nsmr/envs/consts.py
nsmr/envs/nsmr.py
nsmr/envs/renderer.py
nsmr/envs/layouts/large_map.json
nsmr/envs/layouts/large_map_collision_map.pkl
nsmr/envs/layouts/no_object.json
nsmr/envs/layouts/no_object_collision_map.pkl
nsmr/envs/layouts/simple_map.json
nsmr/envs/layouts/simple_map_collision_map.pkl
nsmr/envs/obs/raycasting.c
nsmr/envs/obs/raycasting.cpython-36m-darwin.so
nsmr/envs/obs/raycasting.cpython-38-darwin.so
nsmr/envs/obs/raycasting.pyx
nsmr-0.2.0.dist-info/LICENSE
nsmr-0.2.0.dist-info/METADATA
nsmr-0.2.0.dist-info/WHEEL
nsmr-0.2.0.dist-info/top_level.txt
nsmr-0.2.0.dist-info/RECORD
